pysfmov.py
pysfmov-0.2.dist-info/LICENSE.txt
pysfmov-0.2.dist-info/METADATA
pysfmov-0.2.dist-info/WHEEL
pysfmov-0.2.dist-info/top_level.txt
pysfmov-0.2.dist-info/RECORD
